zsh_kernel/__init__.py
zsh_kernel/__main__.py
zsh_kernel/banner.txt
zsh_kernel/conf.py
zsh_kernel/install.py
zsh_kernel/kernel.py
zsh_kernel/kernel_test.py
zsh_kernel-2.0.dist-info/LICENSE
zsh_kernel-2.0.dist-info/METADATA
zsh_kernel-2.0.dist-info/WHEEL
zsh_kernel-2.0.dist-info/top_level.txt
zsh_kernel-2.0.dist-info/RECORD
